{"color":{
    "2011":{
        "property": "usage",
        "stops": [
          [698949,"#edf8fb"],
          [1301757,"#b2e2e2"],
          [2170008,"#66c2a4"],
          [3554958,"#2ca25f"],
          [6058150,"#006d2c"]
        ]
    },
    "2012":{
        "property": "usage",
        "stops": [
          [656897,"#edf8fb"],
          [1227618,"#b2e2e2"],
          [2272335,"#66c2a4"],
          [3795494,"#2ca25f"],
          [6622218,"#006d2c"]
        ]
    },
    "2013":{
        "property": "usage",
        "stops": [
          [616406,"#edf8fb"],
          [1221061,"#b2e2e2"],
          [2514813,"#66c2a4"],
          [4353626,"#2ca25f"],
          [8550866,"#006d2c"]
        ]
    },
    "2014":{
        "property": "usage",
        "stops": [
          [597775,"#edf8fb"],
          [1116670,"#b2e2e2"],
          [1949036,"#66c2a4"],
          [3621061,"#2ca25f"],
          [6053778,"#006d2c"]
        ]
    },
    "2015":{
        "property": "usage",
        "stops": [
          [515810,"#edf8fb"],
          [1007593,"#b2e2e2"],
          [1799005,"#66c2a4"],
          [3046920,"#2ca25f"],
          [5249990,"#006d2c"]
        ]
    },
    "2016":{
        "property": "usage",
        "stops": [
          [515776,"#edf8fb"],
          [1008758,"#b2e2e2"],
          [1747216,"#66c2a4"],
          [3239579,"#2ca25f"],
          [5079612,"#006d2c"]
        ]
    }}
}